AUTHORS.txt
CHANGES.rst
CLASSIFIERS.txt
LICENSE
MANIFEST.in
README.rst
REQUIREMENTS.txt
setup.py
sphinx_fontawesome/__init__.py
sphinx_fontawesome/__init__.pyc
sphinx_fontawesome/constant.py
sphinx_fontawesome/constant.pyc
sphinx_fontawesome.egg-info/PKG-INFO
sphinx_fontawesome.egg-info/SOURCES.txt
sphinx_fontawesome.egg-info/dependency_links.txt
sphinx_fontawesome.egg-info/requires.txt
sphinx_fontawesome.egg-info/top_level.txt