Metadata-Version: 1.1
Name: sphinx-fontawesome
Version: 0.0.5
Summary: add directive for fontawesome in sphinx
Home-page: https://github.com/fraoustin/sphinx_fontawesome
Author: Frédéric Aoustin
Author-email: fraoustin@gmail.com
License: UNKNOWN
Platform: UNKNOWN
Classifier: Programming Language :: Python
Classifier: Development Status :: 3 - Alpha
Classifier: License :: OSI Approved :: GNU General Public License v2 (GPLv2)
Classifier: Natural Language :: French
Classifier: Operating System :: OS Independent
Classifier: Programming Language :: Python :: 2.7
Classifier: Programming Language :: Python :: 3
Classifier: Programming Language :: Python :: 3.0
Classifier: Programming Language :: Python :: 3.1
Classifier: Programming Language :: Python :: 3.2
Classifier: Programming Language :: Python :: 3.3
Classifier: Programming Language :: Python :: 3.4
Classifier: Topic :: Software Development :: Documentation
Classifier: Topic :: Internet
